{"doc_id": "375d2411-ae1c-4dd7-a86f-e92e2c41ee60", "doc_name": "FruitDexImages", "doc_version": "cddc0c08a77f02c87454eed8a0076fa0", "format": "tf_lite", "version": 20, "inputs": {"Image": {"dtype": "float32", "shape": [null, 224, 224, 3], "name": "Image"}}, "outputs": {"Confidences": {"dtype": "float32", "shape": [null, 33], "name": "375d2411-ae1c-4dd7-a86f-e92e2c41ee60.19e19720-fbd0-4671-85c8-35b9200325ff/dense_2/Softmax"}}, "tags": [], "classes": {"Label": ["Akee", "Almond", "Avocado (Zaboca)", "Banana", "Barbadine", "Breadfruit", "Cantaloupe", "Carillie", "Cashew", "Chalta", "Chataigne", "Chenet", "Chinese Tamarind", "Christophene", "Cocoa", "Custard Apple", "Fat Pork", "Governor Plum", "Grapefruit", "Guava", "Jack Fruit", "Lime", "Lychee", "Mandarin", "Mango", "Miracle fruit", "Noni", "Pawpaw", "Peewah", "Please Scan a Fruit", "Pomerac", "Pommecythere", "Star Fruit (Five Fingers)"]}, "filename": "saved_model.tflite", "export_model_version": 1}